setup.py
distributions/Binomialdistribution.py
distributions/Gaussiandistribution.py
distributions/Generaldistribution.py
distributions/__init__.py
proba_dist.egg-info/PKG-INFO
proba_dist.egg-info/SOURCES.txt
proba_dist.egg-info/dependency_links.txt
proba_dist.egg-info/not-zip-safe
proba_dist.egg-info/top_level.txt