Metadata-Version: 1.0
Name: proba-dist
Version: 0.2
Summary: Gaussian and Binomial distributions
Home-page: UNKNOWN
Author: Emmanuel Siaw Darko
Author-email: immanuelsiawdarko@gmail.com
License: UNKNOWN
Platform: UNKNOWN
